MANIFEST.in
README.md
setup.py
valhalla/__init__.py
valhalla.egg-info/PKG-INFO
valhalla.egg-info/SOURCES.txt
valhalla.egg-info/dependency_links.txt
valhalla.egg-info/requires.txt
valhalla.egg-info/top_level.txt
valhalla/filters/__init__.py
valhalla/filters/casting.py
valhalla/filters/chrono.py
valhalla/filters/collection.py
valhalla/filters/logical.py
valhalla/filters/money.py
valhalla/filters/numerical.py
valhalla/filters/strings.py
valhalla/filters/web.py
valhalla/tests/__init__.py
valhalla/tests/test_casting.py
valhalla/tests/test_chrono.py
valhalla/tests/test_collection.py
valhalla/tests/test_logical.py
valhalla/tests/test_money.py
valhalla/tests/test_numerical.py
valhalla/tests/test_strings.py
valhalla/tests/test_valhalla.py
valhalla/tests/test_web.py