Metadata-Version: 1.1
Name: valhalla
Version: 0.0.4
Summary: A slim validation library with a very elegant API designed to afford the least amount of typing.
Home-page: http://github.com/petermelias/valhalla
Author: Peter M. Elias
Author-email: petermelias@gmail.com
License: MIT
Platform: UNKNOWN
Classifier: Environment :: Web Environment
Classifier: Intended Audience :: Developers
Classifier: License :: OSI Approved :: MIT License
Classifier: Operating System :: OS Independent
Classifier: Programming Language :: Python
Classifier: Topic :: Internet :: WWW/HTTP :: Dynamic Content
Classifier: Topic :: Software Development :: Libraries :: Python Modules
